{
  "type": "Front-end",
  "feed": {
    "CSS Tricks": {
      "items": [
        {
          "creator": "Geoff Graham",
          "title": "CSS Length Units",
          "link": "https://css-tricks.com/css-length-units/",
          "pubDate": "Mon, 03 Jun 2024 19:22:02 +0000",
          "content:encoded": "",
          "content:encodedSnippet": "",
          "dc:creator": "Geoff Graham",
          "comments": "https://css-tricks.com/css-length-units/#comments",
          "content": "",
          "contentSnippet": "",
          "guid": "https://css-tricks.com/?p=375815",
          "categories": [
            "Article",
            "Guide Collection",
            "container units",
            "units"
          ],
          "isoDate": "2024-06-03T19:22:02.000Z",
          "summary": ""
        },
        {
          "creator": "Chris DeMars",
          "title": "Demystifying Screen Readers: Accessible Forms & Best Practices",
          "link": "https://css-tricks.com/demystifying-screen-readers-accessible-forms-best-practices/",
          "pubDate": "Fri, 19 Apr 2024 14:26:47 +0000",
          "content:encoded": "",
          "content:encodedSnippet": "",
          "dc:creator": "Chris DeMars",
          "comments": "https://css-tricks.com/demystifying-screen-readers-accessible-forms-best-practices/#comments",
          "content": "",
          "contentSnippet": "",
          "guid": "https://css-tricks.com/?p=377733",
          "categories": [
            "Article",
            "accessibility",
            "forms"
          ],
          "isoDate": "2024-04-19T14:26:47.000Z",
          "summary": ""
        },
        {
          "creator": "Chris DeMars",
          "title": "Managing User Focus with :focus-visible",
          "link": "https://css-tricks.com/managing-user-focus-with-focus-visible/",
          "pubDate": "Fri, 05 Apr 2024 22:13:47 +0000",
          "content:encoded": "",
          "content:encodedSnippet": "",
          "dc:creator": "Chris DeMars",
          "comments": "https://css-tricks.com/managing-user-focus-with-focus-visible/#comments",
          "content": "",
          "contentSnippet": "",
          "guid": "https://css-tricks.com/?p=377702",
          "categories": [
            "Article",
            "accessibility",
            "forms"
          ],
          "isoDate": "2024-04-05T22:13:47.000Z",
          "summary": ""
        },
        {
          "creator": "Chris DeMars",
          "title": "The Power of :has() in CSS",
          "link": "https://css-tricks.com/the-power-of-has-in-css/",
          "pubDate": "Sat, 30 Mar 2024 02:07:57 +0000",
          "content:encoded": "",
          "content:encodedSnippet": "",
          "dc:creator": "Chris DeMars",
          "comments": "https://css-tricks.com/the-power-of-has-in-css/#comments",
          "content": "",
          "contentSnippet": "",
          "guid": "https://css-tricks.com/?p=377635",
          "categories": [
            "Article",
            ":has",
            "CSS"
          ],
          "isoDate": "2024-03-30T02:07:57.000Z",
          "summary": ""
        },
        {
          "creator": "Chris DeMars",
          "title": "Accessible Forms with Pseudo Classes",
          "link": "https://css-tricks.com/accessible-forms-with-pseudo-classes/",
          "pubDate": "Fri, 22 Mar 2024 18:52:31 +0000",
          "content:encoded": "",
          "content:encodedSnippet": "",
          "dc:creator": "Chris DeMars",
          "comments": "https://css-tricks.com/accessible-forms-with-pseudo-classes/#comments",
          "content": "",
          "contentSnippet": "",
          "guid": "https://css-tricks.com/?p=377565",
          "categories": [
            "Article",
            "accessibility",
            "CSS",
            "focus",
            "forms",
            "HTML",
            "semantics"
          ],
          "isoDate": "2024-03-22T18:52:31.000Z",
          "summary": ""
        }
      ],
      "feedUrl": "https://css-tricks.com/feed/",
      "image": {
        "link": "https://css-tricks.com",
        "url": "https://i0.wp.com/css-tricks.com/wp-content/uploads/2021/07/star.png?fit=32%2C32&ssl=1",
        "title": "CSS-Tricks",
        "width": "32",
        "height": "32"
      },
      "paginationLinks": {
        "self": "https://css-tricks.com/feed/"
      },
      "title": "CSS-Tricks",
      "description": "Tips, Tricks, and Techniques on using Cascading Style Sheets.",
      "generator": "https://wordpress.org/?v=6.5.2",
      "link": "https://css-tricks.com",
      "language": "en-US",
      "lastBuildDate": "Mon, 03 Jun 2024 19:23:58 +0000"
    },
    "CSS In Real Life": {
      "items": [
        {
          "title": "Progressively Enhanced Popover Toggletips",
          "link": "https://css-irl.info/progressively-enhanced-popover-toggletips/",
          "pubDate": "2024-05-27T00:00:00.000Z",
          "content": "",
          "contentSnippet": "",
          "id": "https://css-irl.info/progressively-enhanced-popover-toggletips/",
          "isoDate": "2024-05-27T00:00:00.000Z",
          "content:encoded": "",
          "content:encodedSnippet": "",
          "summary": ""
        },
        {
          "title": "Perspective",
          "link": "https://css-irl.info/perspective/",
          "pubDate": "2024-05-24T00:00:00.000Z",
          "content": "",
          "contentSnippet": "",
          "id": "https://css-irl.info/perspective/",
          "isoDate": "2024-05-24T00:00:00.000Z",
          "content:encoded": "",
          "content:encodedSnippet": "",
          "summary": ""
        },
        {
          "title": "Anchor Positioning and the Popover API for a JS-Free Site Menu",
          "link": "https://css-irl.info/anchor-positioning-and-the-popover-api/",
          "pubDate": "2024-05-14T00:00:00.000Z",
          "content": "",
          "contentSnippet": "",
          "id": "https://css-irl.info/anchor-positioning-and-the-popover-api/",
          "isoDate": "2024-05-14T00:00:00.000Z",
          "content:encoded": "",
          "content:encodedSnippet": "",
          "summary": ""
        },
        {
          "title": "RSS is Good, Isn’t It?!",
          "link": "https://css-irl.info/rss-is-good-isnt-it/",
          "pubDate": "2024-05-13T00:00:00.000Z",
          "content": "",
          "contentSnippet": "",
          "id": "https://css-irl.info/rss-is-good-isnt-it/",
          "isoDate": "2024-05-13T00:00:00.000Z",
          "content:encoded": "",
          "content:encodedSnippet": "",
          "summary": ""
        },
        {
          "title": "Manifesto for a Humane Web",
          "link": "https://css-irl.info/manifesto-for-a-humane-web/",
          "pubDate": "2024-05-10T00:00:00.000Z",
          "content": "",
          "contentSnippet": "",
          "id": "https://css-irl.info/manifesto-for-a-humane-web/",
          "isoDate": "2024-05-10T00:00:00.000Z",
          "content:encoded": "",
          "content:encodedSnippet": "",
          "summary": ""
        }
      ],
      "link": "https://css-irl.info/rss.xml/",
      "feedUrl": "https://css-irl.info/rss.xml/",
      "title": "CSS In Real Life",
      "lastBuildDate": "2024-05-27T00:00:00Z"
    },
    "A list Apart": {
      "items": [
        {
          "creator": "\n\t\t\t\tby \t\t\t\t\t",
          "date": "\n\t\t\t\t\t2024-05-30T18:04:43+00:00\t\t\t\t",
          "title": "\n\t\t\t\t\tUser Research Is Storytelling\t\t\t\t",
          "link": "\n\t\t\t\t\thttps://alistapart.com/article/user-research-is-storytelling/\t\t\t\t",
          "author": "\n\t\t\t\tby \t\t\t\t\t",
          "dc:date": "\n\t\t\t\t\t2024-05-30T18:04:43+00:00\t\t\t\t",
          "content": "",
          "contentSnippet": "",
          "guid": "\n\t\t\t\t\thttps://alistapart.com/article/user-research-is-storytelling/\t\t\t\t",
          "isoDate": "2024-05-30T18:04:43.000Z",
          "content:encoded": "",
          "content:encodedSnippet": "",
          "summary": ""
        },
        {
          "creator": "\n\t\t\t\tby , \t\t\t\t\t",
          "date": "\n\t\t\t\t\t2024-04-16T19:51:34+00:00\t\t\t\t",
          "title": "\n\t\t\t\t\tTo Ignite a Personalization Practice, Run this Prepersonalization Workshop\t\t\t\t",
          "link": "\n\t\t\t\t\thttps://alistapart.com/article/prepersonalization-workshop/\t\t\t\t",
          "author": "\n\t\t\t\tby , \t\t\t\t\t",
          "dc:date": "\n\t\t\t\t\t2024-04-16T19:51:34+00:00\t\t\t\t",
          "content": "",
          "contentSnippet": "",
          "guid": "\n\t\t\t\t\thttps://alistapart.com/article/prepersonalization-workshop/\t\t\t\t",
          "isoDate": "2024-04-16T19:51:34.000Z",
          "content:encoded": "",
          "content:encodedSnippet": "",
          "summary": ""
        },
        {
          "creator": "\n\t\t\t\tby \t\t\t\t\t",
          "date": "\n\t\t\t\t\t2024-02-29T14:45:00+00:00\t\t\t\t",
          "title": "\n\t\t\t\t\tThe Wax and the Wane of the Web\t\t\t\t",
          "link": "\n\t\t\t\t\thttps://alistapart.com/article/the-wax-and-the-wane-of-the-web/\t\t\t\t",
          "author": "\n\t\t\t\tby \t\t\t\t\t",
          "dc:date": "\n\t\t\t\t\t2024-02-29T14:45:00+00:00\t\t\t\t",
          "content": "",
          "contentSnippet": "",
          "guid": "\n\t\t\t\t\thttps://alistapart.com/article/the-wax-and-the-wane-of-the-web/\t\t\t\t",
          "isoDate": "2024-02-29T14:45:00.000Z",
          "content:encoded": "",
          "content:encodedSnippet": "",
          "summary": ""
        },
        {
          "creator": "\n\t\t\t\tby \t\t\t\t\t",
          "date": "\n\t\t\t\t\t2024-02-07T14:00:00+00:00\t\t\t\t",
          "title": "\n\t\t\t\t\tOpportunities for AI in Accessibility\t\t\t\t",
          "link": "\n\t\t\t\t\thttps://alistapart.com/article/opportunities-for-ai-in-accessibility/\t\t\t\t",
          "author": "\n\t\t\t\tby \t\t\t\t\t",
          "dc:date": "\n\t\t\t\t\t2024-02-07T14:00:00+00:00\t\t\t\t",
          "content": "",
          "contentSnippet": "",
          "guid": "\n\t\t\t\t\thttps://alistapart.com/article/opportunities-for-ai-in-accessibility/\t\t\t\t",
          "isoDate": "2024-02-07T14:00:00.000Z",
          "content:encoded": "",
          "content:encodedSnippet": "",
          "summary": ""
        },
        {
          "creator": "\n\t\t\t\tby \t\t\t\t\t",
          "date": "\n\t\t\t\t\t2024-01-29T15:53:09+00:00\t\t\t\t",
          "title": "\n\t\t\t\t\tI am a creative.\t\t\t\t",
          "link": "\n\t\t\t\t\thttps://alistapart.com/article/i-am-a-creative/\t\t\t\t",
          "author": "\n\t\t\t\tby \t\t\t\t\t",
          "dc:date": "\n\t\t\t\t\t2024-01-29T15:53:09+00:00\t\t\t\t",
          "content": "",
          "contentSnippet": "",
          "guid": "\n\t\t\t\t\thttps://alistapart.com/article/i-am-a-creative/\t\t\t\t",
          "isoDate": "2024-01-29T15:53:09.000Z",
          "content:encoded": "",
          "content:encodedSnippet": "",
          "summary": ""
        }
      ],
      "creator": "The fine folks at A List Apart",
      "title": "\n\t\t\tA List Apart: The Full Feed\t\t",
      "description": "Articles for people who make web sites.",
      "link": "\n\t\t\thttps://alistapart.com\t\t"
    },
    "Web Designer Depot": {
      "items": [
        {
          "title": "Exciting New Tools for Designers, June 2024",
          "link": "https://www.webdesignerdepot.com/exciting-new-tools-for-designers-june-2024/",
          "pubDate": "Mon, 03 Jun 2024 05:30:00 -0700",
          "enclosure": {
            "url": "https://www.webdesignerdepot.com/assets/posts/featured/01-timeframe.jpg",
            "length": "0",
            "type": "image/jpg"
          },
          "content": "",
          "contentSnippet": "",
          "guid": "https://www.webdesignerdepot.com/exciting-new-tools-for-designers-june-2024/",
          "categories": [
            "Compilations"
          ],
          "isoDate": "2024-06-03T12:30:00.000Z",
          "content:encoded": "",
          "content:encodedSnippet": "",
          "summary": ""
        },
        {
          "title": "3 Essential Design Trends, June 2024",
          "link": "https://www.webdesignerdepot.com/design-trends-june-2024/",
          "pubDate": "Mon, 27 May 2024 05:30:00 -0700",
          "enclosure": {
            "url": "https://www.webdesignerdepot.com/assets/posts/featured/achen.jpg",
            "length": "0",
            "type": "image/jpg"
          },
          "content": "",
          "contentSnippet": "",
          "guid": "https://www.webdesignerdepot.com/design-trends-june-2024/",
          "categories": [
            "Compilations"
          ],
          "isoDate": "2024-05-27T12:30:00.000Z",
          "content:encoded": "",
          "content:encodedSnippet": "",
          "summary": ""
        },
        {
          "title": "15 Best New Fonts, May 2024",
          "link": "https://www.webdesignerdepot.com/best-fonts-may-2024/",
          "pubDate": "Mon, 20 May 2024 05:30:00 -0700",
          "enclosure": {
            "url": "https://www.webdesignerdepot.com/assets/posts/featured/racina.jpg",
            "length": "0",
            "type": "image/jpg"
          },
          "content": "",
          "contentSnippet": "",
          "guid": "https://www.webdesignerdepot.com/best-fonts-may-2024/",
          "categories": [
            "Fonts"
          ],
          "isoDate": "2024-05-20T12:30:00.000Z",
          "content:encoded": "",
          "content:encodedSnippet": "",
          "summary": ""
        },
        {
          "title": "How to Reduce The Carbon Footprint of Your Website",
          "link": "https://www.webdesignerdepot.com/reduce-website-carbon-footprints/",
          "pubDate": "Thu, 16 May 2024 05:30:00 -0700",
          "enclosure": {
            "url": "https://www.webdesignerdepot.com/assets/posts/featured/green-laptop.jpg",
            "length": "0",
            "type": "image/jpg"
          },
          "content": "",
          "contentSnippet": "",
          "guid": "https://www.webdesignerdepot.com/reduce-website-carbon-footprints/",
          "categories": [
            "Development"
          ],
          "isoDate": "2024-05-16T12:30:00.000Z",
          "content:encoded": "",
          "content:encodedSnippet": "",
          "summary": ""
        },
        {
          "title": "20 Best New Websites, May 2024",
          "link": "https://www.webdesignerdepot.com/best-websites-may-2024/",
          "pubDate": "Mon, 13 May 2024 05:30:00 -0700",
          "enclosure": {
            "url": "https://www.webdesignerdepot.com/assets/posts/featured/cc.jpg",
            "length": "0",
            "type": "image/jpg"
          },
          "content": "",
          "contentSnippet": "",
          "guid": "https://www.webdesignerdepot.com/best-websites-may-2024/",
          "categories": [
            "Compilations"
          ],
          "isoDate": "2024-05-13T12:30:00.000Z",
          "content:encoded": "",
          "content:encodedSnippet": "",
          "summary": ""
        }
      ],
      "feedUrl": "https://www.webdesignerdepot.com/feed.rss",
      "image": {
        "link": "https://www.webdesignerdepot.com",
        "url": "https://www.webdesignerdepot.com/assets/ui/brand/rss_banner.png",
        "title": "Web Designer Depot",
        "width": "144",
        "height": "144"
      },
      "paginationLinks": {
        "self": "https://www.webdesignerdepot.com/feed.rss"
      },
      "title": "Web Designer Depot",
      "description": "Web Design Resources and Tutorials",
      "pubDate": "Fri, 07 Jun 2024 00:07:02 -0700",
      "link": "https://www.webdesignerdepot.com",
      "language": "en-us",
      "copyright": "Copyright Web Designer Depot, all rights reserved."
    },
    "Brad Frost": {
      "items": [
        {
          "title": "A rare use case for em units",
          "link": "https://bradfrost.com/blog/post/a-rare-use-case-for-em-units/",
          "pubDate": "2024-06-04T19:52:23.000Z",
          "author": "Brad Frost",
          "content": "",
          "contentSnippet": "",
          "summary": "",
          "id": "https://bradfrost.com/?p=20290",
          "isoDate": "2024-06-04T19:52:23.000Z",
          "content:encoded": "",
          "content:encodedSnippet": ""
        },
        {
          "title": "Sentient Design: AI and the Next Chapter of UX &#8211; Big Medium",
          "link": "https://bradfrost.com/blog/link/sentient-design-ai-and-the-next-chapter-of-ux-big-medium/",
          "pubDate": "2024-06-04T16:01:12.000Z",
          "author": "Brad Frost",
          "content": "",
          "contentSnippet": "",
          "summary": "",
          "id": "https://bradfrost.com/?p=20288",
          "isoDate": "2024-06-04T16:01:12.000Z",
          "content:encoded": "",
          "content:encodedSnippet": ""
        },
        {
          "title": "Be gone, vile rectangle!",
          "link": "https://bradfrost.com/blog/post/be-gone-vile-rectangle/",
          "pubDate": "2024-05-23T13:58:09.000Z",
          "author": "Brad Frost",
          "content": "",
          "contentSnippet": "",
          "summary": "",
          "id": "https://bradfrost.com/?p=20241",
          "isoDate": "2024-05-23T13:58:09.000Z",
          "content:encoded": "",
          "content:encodedSnippet": ""
        },
        {
          "title": "Every Sample from Paul’s Boutique by the Beastie Boys",
          "link": "https://bradfrost.com/blog/link/every-sample-from-pauls-boutique-by-the-beastie-boys/",
          "pubDate": "2024-05-22T20:26:14.000Z",
          "author": "Brad Frost",
          "content": "",
          "contentSnippet": "",
          "summary": "",
          "id": "https://bradfrost.com/?p=20260",
          "isoDate": "2024-05-22T20:26:14.000Z",
          "content:encoded": "",
          "content:encodedSnippet": ""
        },
        {
          "title": "The age of average (encore) — Alex Murrell",
          "link": "https://bradfrost.com/blog/link/the-age-of-average-encore-alex-murrell/",
          "pubDate": "2024-05-17T20:15:02.000Z",
          "author": "Brad Frost",
          "content": "",
          "contentSnippet": "",
          "summary": "",
          "id": "https://bradfrost.com/?p=20227",
          "isoDate": "2024-05-17T20:15:02.000Z",
          "content:encoded": "",
          "content:encodedSnippet": ""
        }
      ],
      "link": "https://bradfrost.com",
      "feedUrl": "https://bradfrost.com/feed/atom/",
      "title": "Brad Frost",
      "lastBuildDate": "2024-06-04T19:52:23Z"
    },
    "Jonathan Suh": {
      "items": [
        {
          "title": "Animated Toggle in React Native",
          "link": "https://jonsuh.com/blog/animated-toggle-react-native/",
          "pubDate": "2018-08-20T11:00:00.000Z",
          "author": "Jonathan Suh",
          "content": "",
          "contentSnippet": "",
          "id": "https://jonsuh.com/blog/animated-toggle-react-native/",
          "isoDate": "2018-08-20T11:00:00.000Z",
          "content:encoded": "",
          "content:encodedSnippet": "",
          "summary": ""
        },
        {
          "title": "Slow Down—You Need It",
          "link": "https://jonsuh.com/blog/slow-down-you-need-it/",
          "pubDate": "2017-11-03T11:00:00.000Z",
          "author": "Jonathan Suh",
          "content": "",
          "contentSnippet": "",
          "id": "https://jonsuh.com/blog/slow-down-you-need-it/",
          "isoDate": "2017-11-03T11:00:00.000Z",
          "content:encoded": "",
          "content:encodedSnippet": "",
          "summary": ""
        },
        {
          "title": "JavaScript Templating Without a Library",
          "link": "https://jonsuh.com/blog/javascript-templating-without-a-library/",
          "pubDate": "2015-11-13T12:00:00.000Z",
          "author": "Jonathan Suh",
          "content": "",
          "contentSnippet": "",
          "id": "https://jonsuh.com/blog/javascript-templating-without-a-library/",
          "isoDate": "2015-11-13T12:00:00.000Z",
          "content:encoded": "",
          "content:encodedSnippet": "",
          "summary": ""
        },
        {
          "title": "The Story Behind “100 Days of Scriptures”",
          "link": "https://jonsuh.com/blog/the-story-behind-100-days-of-scriptures/",
          "pubDate": "2015-10-29T11:00:00.000Z",
          "author": "Jonathan Suh",
          "content": "",
          "contentSnippet": "",
          "id": "https://jonsuh.com/blog/the-story-behind-100-days-of-scriptures/",
          "isoDate": "2015-10-29T11:00:00.000Z",
          "content:encoded": "",
          "content:encodedSnippet": "",
          "summary": ""
        },
        {
          "title": "Ugmonk Waxed Canvas Messenger Bag Review",
          "link": "https://jonsuh.com/blog/ugmonk-messenger-bag/",
          "pubDate": "2015-10-05T11:00:00.000Z",
          "author": "Jonathan Suh",
          "content": "",
          "contentSnippet": "",
          "id": "https://jonsuh.com/blog/ugmonk-messenger-bag/",
          "isoDate": "2015-10-05T11:00:00.000Z",
          "content:encoded": "",
          "content:encodedSnippet": "",
          "summary": ""
        }
      ],
      "link": "https://jonsuh.com/",
      "title": "Jonathan Suh",
      "lastBuildDate": "2018-08-20T08:02:26-05:00"
    },
    "CSS Wizardry": {
      "items": [
        {
          "title": "Correctly Configure (Pre) Connections",
          "link": "https://csswizardry.com/2023/12/correctly-configure-preconnections/",
          "pubDate": "Sat, 09 Dec 2023 19:17:04 +0000",
          "content": "",
          "contentSnippet": "",
          "guid": "https://csswizardry.com/2023/12/correctly-configure-preconnections/",
          "isoDate": "2023-12-09T19:17:04.000Z",
          "content:encoded": "",
          "content:encodedSnippet": "",
          "summary": ""
        },
        {
          "title": "The Three Cs: 🤝 Concatenate, 🗜️ Compress, 🗳️ Cache",
          "link": "https://csswizardry.com/2023/10/the-three-c-concatenate-compress-cache/",
          "pubDate": "Tue, 17 Oct 2023 00:00:00 +0000",
          "content": "",
          "contentSnippet": "",
          "guid": "https://csswizardry.com/2023/10/the-three-c-concatenate-compress-cache/",
          "isoDate": "2023-10-17T00:00:00.000Z",
          "content:encoded": "",
          "content:encodedSnippet": "",
          "summary": ""
        },
        {
          "title": "What Is the Maximum max-age?",
          "link": "https://csswizardry.com/2023/10/what-is-the-maximum-max-age/",
          "pubDate": "Mon, 16 Oct 2023 14:18:39 +0000",
          "content": "",
          "contentSnippet": "",
          "guid": "https://csswizardry.com/2023/10/what-is-the-maximum-max-age/",
          "isoDate": "2023-10-16T14:18:39.000Z",
          "content:encoded": "",
          "content:encodedSnippet": "",
          "summary": ""
        },
        {
          "title": "How to Clear Cache and Cookies on a Customer’s Device",
          "link": "https://csswizardry.com/2023/10/clear-cache-on-customer-device/",
          "pubDate": "Mon, 02 Oct 2023 15:30:49 +0000",
          "content": "",
          "contentSnippet": "",
          "guid": "https://csswizardry.com/2023/10/clear-cache-on-customer-device/",
          "isoDate": "2023-10-02T15:30:49.000Z",
          "content:encoded": "",
          "content:encodedSnippet": "",
          "summary": ""
        },
        {
          "title": "The Ultimate Low-Quality Image Placeholder Technique",
          "link": "https://csswizardry.com/2023/09/the-ultimate-lqip-lcp-technique/",
          "pubDate": "Thu, 28 Sep 2023 18:59:20 +0000",
          "content": "",
          "contentSnippet": "",
          "guid": "https://csswizardry.com/2023/09/the-ultimate-lqip-lcp-technique/",
          "isoDate": "2023-09-28T18:59:20.000Z",
          "content:encoded": "",
          "content:encodedSnippet": "",
          "summary": ""
        }
      ],
      "feedUrl": "https://csswizardry.com/feed.xml",
      "paginationLinks": {
        "self": "https://csswizardry.com/feed.xml"
      },
      "title": "CSS Wizardry",
      "description": "&ndash; Harry Roberts &ndash; Web Performance Consultant",
      "link": "https://csswizardry.com/"
    },
    "Dave Rupert": {
      "items": [
        {
          "title": "A common web component learning blunder",
          "link": "https://daverupert.com/2024/05/cold-turkey-wont-fix-your-javascript-addiction/",
          "pubDate": "Tue, 28 May 2024 14:17:00 +0000",
          "content": "",
          "contentSnippet": "",
          "guid": "https://daverupert.com/2024/05/cold-turkey-wont-fix-your-javascript-addiction/",
          "isoDate": "2024-05-28T14:17:00.000Z",
          "content:encoded": "",
          "content:encodedSnippet": "",
          "summary": ""
        },
        {
          "title": "Dave Goes Microsoft",
          "link": "https://daverupert.com/2024/05/dave-goes-microsoft/",
          "pubDate": "Thu, 16 May 2024 14:02:00 +0000",
          "content": "",
          "contentSnippet": "",
          "guid": "https://daverupert.com/2024/05/dave-goes-microsoft/",
          "isoDate": "2024-05-16T14:02:00.000Z",
          "content:encoded": "",
          "content:encodedSnippet": "",
          "summary": ""
        },
        {
          "title": "A quick light-dark() experiment",
          "link": "https://daverupert.com/2024/05/light-dark-experiment/",
          "pubDate": "Sun, 05 May 2024 15:27:00 +0000",
          "content": "",
          "contentSnippet": "",
          "guid": "https://daverupert.com/2024/05/light-dark-experiment/",
          "isoDate": "2024-05-05T15:27:00.000Z",
          "content:encoded": "",
          "content:encodedSnippet": "",
          "summary": ""
        },
        {
          "title": "Vibe Check №32",
          "link": "https://daverupert.com/2024/05/vibe-check-32/",
          "pubDate": "Sun, 05 May 2024 03:56:00 +0000",
          "content": "",
          "contentSnippet": "",
          "guid": "https://daverupert.com/2024/05/vibe-check-32/",
          "isoDate": "2024-05-05T03:56:00.000Z",
          "content:encoded": "",
          "content:encodedSnippet": "",
          "summary": ""
        },
        {
          "title": "Thoughts on Cosmotechnics",
          "link": "https://daverupert.com/2024/04/thoughts-on-cosmotechnics/",
          "pubDate": "Mon, 29 Apr 2024 01:17:00 +0000",
          "content": "",
          "contentSnippet": "",
          "guid": "https://daverupert.com/2024/04/thoughts-on-cosmotechnics/",
          "isoDate": "2024-04-29T01:17:00.000Z",
          "content:encoded": "",
          "content:encodedSnippet": "",
          "summary": ""
        }
      ],
      "feedUrl": "https://daverupert.com/atom.xml",
      "paginationLinks": {
        "self": "https://daverupert.com/atom.xml"
      },
      "title": "daverupert.com",
      "description": "The personal blog of Dave Rupert, web developer and podcaster from Austin, TX.",
      "link": "https://daverupert.com"
    },
    "Atta Comisan": {
      "items": [
        {
          "title": "Get the length of a Map in JavaScript",
          "link": "https://attacomsian.com/blog/javascript-map-get-length",
          "pubDate": "Sun, 11 Dec 2022 03:38:42 GMT",
          "content:encoded": "",
          "content:encodedSnippet": "",
          "enclosure": {
            "url": "https://attacomsian.com/social-banner/javascript-map-get-length.png",
            "length": "0",
            "type": "image/png"
          },
          "content": "",
          "contentSnippet": "",
          "guid": "z2AXlk3ZAW",
          "categories": [
            {
              "_": "JavaScript",
              "$": {
                "domain": "https://attacomsian.com/topics/javascript"
              }
            }
          ],
          "isoDate": "2022-12-11T03:38:42.000Z",
          "summary": ""
        },
        {
          "title": "Delete an element from a Map in JavaScript",
          "link": "https://attacomsian.com/blog/javascript-map-delete-element",
          "pubDate": "Sun, 11 Dec 2022 03:19:53 GMT",
          "content:encoded": "",
          "content:encodedSnippet": "",
          "enclosure": {
            "url": "https://attacomsian.com/social-banner/javascript-map-delete-element.png",
            "length": "0",
            "type": "image/png"
          },
          "content": "",
          "contentSnippet": "",
          "guid": "f4sTleQDoT",
          "categories": [
            {
              "_": "JavaScript",
              "$": {
                "domain": "https://attacomsian.com/topics/javascript"
              }
            }
          ],
          "isoDate": "2022-12-11T03:19:53.000Z",
          "summary": ""
        },
        {
          "title": "Get the first element of a Map in JavaScript",
          "link": "https://attacomsian.com/blog/javascript-map-get-first-element",
          "pubDate": "Sat, 10 Dec 2022 18:56:41 GMT",
          "content:encoded": "",
          "content:encodedSnippet": "",
          "enclosure": {
            "url": "https://attacomsian.com/social-banner/javascript-map-get-first-element.png",
            "length": "0",
            "type": "image/png"
          },
          "content": "",
          "contentSnippet": "",
          "guid": "MtnCWTRjRm",
          "categories": [
            {
              "_": "JavaScript",
              "$": {
                "domain": "https://attacomsian.com/topics/javascript"
              }
            }
          ],
          "isoDate": "2022-12-10T18:56:41.000Z",
          "summary": ""
        },
        {
          "title": "Get an element from a Map using JavaScript",
          "link": "https://attacomsian.com/blog/javascript-map-get-element",
          "pubDate": "Sat, 10 Dec 2022 18:20:40 GMT",
          "content:encoded": "",
          "content:encodedSnippet": "",
          "enclosure": {
            "url": "https://attacomsian.com/social-banner/javascript-map-get-element.png",
            "length": "0",
            "type": "image/png"
          },
          "content": "",
          "contentSnippet": "",
          "guid": "ahCzYNjTqy",
          "categories": [
            {
              "_": "JavaScript",
              "$": {
                "domain": "https://attacomsian.com/topics/javascript"
              }
            }
          ],
          "isoDate": "2022-12-10T18:20:40.000Z",
          "summary": ""
        },
        {
          "title": "Update an element in a Map using JavaScript",
          "link": "https://attacomsian.com/blog/javascript-map-update-element",
          "pubDate": "Sun, 04 Dec 2022 15:56:58 GMT",
          "content:encoded": "",
          "content:encodedSnippet": "",
          "enclosure": {
            "url": "https://attacomsian.com/social-banner/javascript-map-update-element.png",
            "length": "0",
            "type": "image/png"
          },
          "content": "",
          "contentSnippet": "",
          "guid": "U7Pc0F6vFL",
          "categories": [
            {
              "_": "JavaScript",
              "$": {
                "domain": "https://attacomsian.com/topics/javascript"
              }
            }
          ],
          "isoDate": "2022-12-04T15:56:58.000Z",
          "summary": ""
        }
      ],
      "image": {
        "link": "https://attacomsian.com/",
        "url": "https://attacomsian.com/img/banner.jpg",
        "title": "Atta-Ur-Rehman Shah"
      },
      "title": "Atta-Ur-Rehman Shah",
      "description": "Atta is a Full Stack developer specialized in Java and MEAN Stack. He writes about modern JavaScript, Spring Boot, and all things web development.",
      "generator": "attacomsian.com",
      "link": "https://attacomsian.com/",
      "language": "en",
      "copyright": "&copy; 2020 Atta. All rights reserved.",
      "lastBuildDate": "Fri, 16 Jun 2023 06:32:47 GMT",
      "docs": "https://validator.w3.org/feed/docs/rss2.html"
    },
    "Hidde's Blog": {
      "items": [
        {
          "title": "On authoring tools in EN 301 549",
          "link": "https://hidde.blog/authoring-tools-in-en-301-549/",
          "pubDate": "2024-04-10T00:00:00.000Z",
          "content": "",
          "contentSnippet": "",
          "id": "https://hidde.blog/authoring-tools-in-en-301-549/",
          "isoDate": "2024-04-10T00:00:00.000Z",
          "content:encoded": "",
          "content:encodedSnippet": "",
          "summary": ""
        },
        {
          "title": "On popover accessibility: what the browser does and doesn’t do",
          "link": "https://hidde.blog/popover-accessibility/",
          "pubDate": "2024-03-21T00:00:00.000Z",
          "content": "",
          "contentSnippet": "",
          "id": "https://hidde.blog/popover-accessibility/",
          "isoDate": "2024-03-21T00:00:00.000Z",
          "content:encoded": "",
          "content:encodedSnippet": "",
          "summary": ""
        },
        {
          "title": "Breadcrumbs, buttons and buy-in: Patterns Day 3",
          "link": "https://hidde.blog/patterns-day-3/",
          "pubDate": "2024-03-08T00:00:00.000Z",
          "content": "",
          "contentSnippet": "",
          "id": "https://hidde.blog/patterns-day-3/",
          "isoDate": "2024-03-08T00:00:00.000Z",
          "content:encoded": "",
          "content:encodedSnippet": "",
          "summary": ""
        },
        {
          "title": "“AI” and accessible front-end components: is the nuance generatable?",
          "link": "https://hidde.blog/ai-for-accessible-components/",
          "pubDate": "2024-03-01T00:00:00.000Z",
          "content": "",
          "contentSnippet": "",
          "id": "https://hidde.blog/ai-for-accessible-components/",
          "isoDate": "2024-03-01T00:00:00.000Z",
          "content:encoded": "",
          "content:encodedSnippet": "",
          "summary": ""
        },
        {
          "title": "Sharing links",
          "link": "https://hidde.blog/sharing-links/",
          "pubDate": "2024-01-12T00:00:00.000Z",
          "content": "",
          "contentSnippet": "",
          "id": "https://hidde.blog/sharing-links/",
          "isoDate": "2024-01-12T00:00:00.000Z",
          "content:encoded": "",
          "content:encodedSnippet": "",
          "summary": ""
        }
      ],
      "link": "https://hidde.blog/feed",
      "feedUrl": "https://hidde.blog/feed",
      "title": "Hidde's blog",
      "lastBuildDate": "2024-04-10T00:00:00Z"
    },
    "Zell Wel": {
      "items": [
        {
          "title": "Data Table Accessibility in 2024",
          "link": "https://zellwk.com/blog/data-table-accessibility-2024/",
          "pubDate": "Wed, 08 May 2024 00:00:00 GMT",
          "content:encoded": "",
          "content:encodedSnippet": "",
          "content": "",
          "contentSnippet": "",
          "guid": "https://zellwk.com/blog/data-table-accessibility-2024/",
          "categories": [
            "Accessibility",
            "Html"
          ],
          "isoDate": "2024-05-08T00:00:00.000Z",
          "summary": ""
        },
        {
          "title": "Found the Light",
          "link": "https://zellwk.com/blog/found-the-light/",
          "pubDate": "Mon, 06 May 2024 00:00:00 GMT",
          "content:encoded": "",
          "content:encodedSnippet": "",
          "content": "",
          "contentSnippet": "",
          "guid": "https://zellwk.com/blog/found-the-light/",
          "categories": [
            "Reflection",
            "Musings",
            "Announcements"
          ],
          "isoDate": "2024-05-06T00:00:00.000Z",
          "summary": ""
        },
        {
          "title": "Collecting Payments with Stripe while using Astro",
          "link": "https://zellwk.com/blog/stripe-astro-recipe/",
          "pubDate": "Mon, 06 May 2024 00:00:00 GMT",
          "content:encoded": "",
          "content:encodedSnippet": "",
          "content": "",
          "contentSnippet": "",
          "guid": "https://zellwk.com/blog/stripe-astro-recipe/",
          "categories": [
            "Stripe",
            "Astro",
            "Astro recipe"
          ],
          "isoDate": "2024-05-06T00:00:00.000Z",
          "summary": ""
        },
        {
          "title": "Easy way to remove inline styles",
          "link": "https://zellwk.com/blog/remove-inline-styles/",
          "pubDate": "Wed, 17 Apr 2024 00:00:00 GMT",
          "content:encoded": "",
          "content:encodedSnippet": "",
          "content": "",
          "contentSnippet": "",
          "guid": "https://zellwk.com/blog/remove-inline-styles/",
          "categories": [
            "Css"
          ],
          "isoDate": "2024-04-17T00:00:00.000Z",
          "summary": ""
        },
        {
          "title": "Understanding and using npm exports",
          "link": "https://zellwk.com/blog/npm-exports/",
          "pubDate": "Tue, 16 Apr 2024 00:00:00 GMT",
          "content:encoded": "",
          "content:encodedSnippet": "",
          "content": "",
          "contentSnippet": "",
          "guid": "https://zellwk.com/blog/npm-exports/",
          "categories": [
            "Node",
            "Npm"
          ],
          "isoDate": "2024-04-16T00:00:00.000Z",
          "summary": ""
        }
      ],
      "title": "Zell Liew",
      "description": "This is where I share the things I know and learned about Web Development and Web Design.",
      "link": "https://zellwk.com/"
    },
    "Go Make Things": {
      "items": [
        {
          "title": "The challenge with Netlify, Vercel, Cloudflare, and so on",
          "link": "https://gomakethings.com/the-challenge-with-netlify-vercel-cloudflare-and-so-on/",
          "pubDate": "Thu, 06 Jun 2024 10:30:00 -0400",
          "content:encoded": "",
          "content:encodedSnippet": "",
          "content": "",
          "contentSnippet": "",
          "guid": "https://gomakethings.com/the-challenge-with-netlify-vercel-cloudflare-and-so-on/",
          "isoDate": "2024-06-06T14:30:00.000Z",
          "summary": ""
        },
        {
          "title": "Learning to code",
          "link": "https://gomakethings.com/learning-to-code/",
          "pubDate": "Wed, 05 Jun 2024 10:30:00 -0400",
          "content:encoded": "",
          "content:encodedSnippet": "",
          "content": "",
          "contentSnippet": "",
          "guid": "https://gomakethings.com/learning-to-code/",
          "isoDate": "2024-06-05T14:30:00.000Z",
          "summary": ""
        },
        {
          "title": "A line of code saved is a line of code earned",
          "link": "https://gomakethings.com/a-line-of-code-saved-is-a-line-of-code-earned/",
          "pubDate": "Tue, 04 Jun 2024 10:30:00 -0400",
          "content:encoded": "",
          "content:encodedSnippet": "",
          "content": "",
          "contentSnippet": "",
          "guid": "https://gomakethings.com/a-line-of-code-saved-is-a-line-of-code-earned/",
          "isoDate": "2024-06-04T14:30:00.000Z",
          "summary": ""
        },
        {
          "title": "Every dependency is a potential vulnerability",
          "link": "https://gomakethings.com/every-dependency-is-a-potential-vulnerability/",
          "pubDate": "Mon, 03 Jun 2024 10:30:00 -0400",
          "content:encoded": "",
          "content:encodedSnippet": "",
          "content": "",
          "contentSnippet": "",
          "guid": "https://gomakethings.com/every-dependency-is-a-potential-vulnerability/",
          "isoDate": "2024-06-03T14:30:00.000Z",
          "summary": ""
        },
        {
          "title": "The different static site generators (and which one to choose)",
          "link": "https://gomakethings.com/the-different-static-site-generators-and-which-one-to-choose/",
          "pubDate": "Fri, 31 May 2024 10:30:00 -0400",
          "content:encoded": "",
          "content:encodedSnippet": "",
          "content": "",
          "contentSnippet": "",
          "guid": "https://gomakethings.com/the-different-static-site-generators-and-which-one-to-choose/",
          "isoDate": "2024-05-31T14:30:00.000Z",
          "summary": ""
        }
      ],
      "feedUrl": "https://gomakethings.com/feed/index.xml",
      "paginationLinks": {
        "self": "https://gomakethings.com/feed/index.xml"
      },
      "title": "Go Make Things",
      "description": "A simpler, more resilient way to make things for the web.",
      "generator": "Hugo -- gohugo.io",
      "link": "https://gomakethings.com/articles",
      "language": "en-us",
      "lastBuildDate": "Fri, 07 Jun 2024 00:01:13 EST"
    }
  }
}