{
  "type": "Tech",
  "feed": {
    "Tech Crunch": {
      "items": [
        {
          "creator": "Brian Heater",
          "title": "Ray-Ban Meta sunglasses have ‘influencer’ written all over them",
          "link": "https://techcrunch.com/2023/10/17/ray-ban-meta-review/",
          "pubDate": "Tue, 17 Oct 2023 07:01:44 +0000",
          "dc:creator": "Brian Heater",
          "content": "",
          "contentSnippet": "",
          "guid": "https://techcrunch.com/?p=2615266",
          "categories": [
            "Gadgets",
            "Hardware",
            "Facebook",
            "Instagram",
            "meta",
            "meta quest 3",
            "mixed reality",
            "ray ban"
          ],
          "isoDate": "2023-10-17T07:01:44.000Z",
          "content:encoded": "",
          "content:encodedSnippet": "",
          "summary": ""
        },
        {
          "creator": "Ivan Mehta",
          "title": "Snapchat is now allowing websites to embed content",
          "link": "https://techcrunch.com/2023/10/16/snapchat-is-now-allowing-websites-to-embed-content/",
          "pubDate": "Tue, 17 Oct 2023 06:02:54 +0000",
          "dc:creator": "Ivan Mehta",
          "content": "",
          "contentSnippet": "",
          "guid": "https://techcrunch.com/?p=2615366",
          "categories": [
            "Apps",
            "Evan Spiegel",
            "Snap",
            "Snapchat"
          ],
          "isoDate": "2023-10-17T06:02:54.000Z",
          "content:encoded": "",
          "content:encodedSnippet": "",
          "summary": ""
        },
        {
          "creator": "Rebecca Bellan",
          "title": "FTX execs blew through $8B; testimony reveals how",
          "link": "https://techcrunch.com/2023/10/16/ftx-execs-blew-through-8b-testimony-reveals-how/",
          "pubDate": "Tue, 17 Oct 2023 03:52:32 +0000",
          "dc:creator": "Rebecca Bellan",
          "content": "",
          "contentSnippet": "",
          "guid": "https://techcrunch.com/?p=2615316",
          "categories": [
            "Crypto",
            "Alameda Research",
            "FTX",
            "Sam Bankman-Fried",
            "SBF"
          ],
          "isoDate": "2023-10-17T03:52:32.000Z",
          "content:encoded": "",
          "content:encodedSnippet": "",
          "summary": ""
        },
        {
          "creator": "Jagmeet Singh",
          "title": "India’s Agnikul gets $26.7M to prepare for commercial space launches",
          "link": "https://techcrunch.com/2023/10/16/agnikul-funding-india-space-tech-startup/",
          "pubDate": "Tue, 17 Oct 2023 03:00:58 +0000",
          "dc:creator": "Jagmeet Singh",
          "content": "",
          "contentSnippet": "",
          "guid": "https://techcrunch.com/?p=2614772",
          "categories": [
            "Space",
            "Startups",
            "Celesta Capital",
            "india",
            "Rocketship VC",
            "space tech"
          ],
          "isoDate": "2023-10-17T03:00:58.000Z",
          "content:encoded": "",
          "content:encodedSnippet": "",
          "summary": ""
        },
        {
          "creator": "Devin Coldewey",
          "title": "Bandcamp’s new owner lays off half the company",
          "link": "https://techcrunch.com/2023/10/16/bandcamps-new-owner-lays-off-half-the-company/",
          "pubDate": "Mon, 16 Oct 2023 22:39:08 +0000",
          "dc:creator": "Devin Coldewey",
          "content": "",
          "contentSnippet": "",
          "guid": "https://techcrunch.com/?p=2615105",
          "categories": [
            "Media & Entertainment",
            "bandcamp",
            "songtradr"
          ],
          "isoDate": "2023-10-16T22:39:08.000Z",
          "content:encoded": "",
          "content:encodedSnippet": "",
          "summary": ""
        },
        {
          "creator": "Aria Alamalhodaei",
          "title": "Max Q: Psyche(d)",
          "link": "https://techcrunch.com/2023/10/16/max-q-psyched/",
          "pubDate": "Mon, 16 Oct 2023 22:00:41 +0000",
          "dc:creator": "Aria Alamalhodaei",
          "content": "",
          "contentSnippet": "",
          "guid": "https://techcrunch.com/?p=2615035",
          "categories": [
            "Space"
          ],
          "isoDate": "2023-10-16T22:00:41.000Z",
          "content:encoded": "",
          "content:encodedSnippet": "",
          "summary": ""
        },
        {
          "creator": "Aisha Malik",
          "title": "Google lobbies against legally mandated age verification for minors",
          "link": "https://techcrunch.com/2023/10/16/google-lobbies-against-legally-mandated-age-verification-for-minors/",
          "pubDate": "Mon, 16 Oct 2023 21:39:05 +0000",
          "dc:creator": "Aisha Malik",
          "content": "",
          "contentSnippet": "",
          "guid": "https://techcrunch.com/?p=2615095",
          "categories": [
            "Government & Policy",
            "children's privacy",
            "Google",
            "online safety"
          ],
          "isoDate": "2023-10-16T21:39:05.000Z",
          "content:encoded": "",
          "content:encodedSnippet": "",
          "summary": ""
        },
        {
          "creator": "Ingrid Lunden",
          "title": "Web Summit derailed by founder’s public fight with those supporting Israel in Hamas war",
          "link": "https://techcrunch.com/2023/10/16/websummit-derailed-by-founders-public-fight-with-those-supporting-israel-in-hamas-conflict/",
          "pubDate": "Mon, 16 Oct 2023 21:14:56 +0000",
          "dc:creator": "Ingrid Lunden",
          "content": "",
          "contentSnippet": "",
          "guid": "https://techcrunch.com/?p=2615006",
          "categories": [
            "Government & Policy",
            "Startups",
            "Hamas-Israel war",
            "web summit"
          ],
          "isoDate": "2023-10-16T21:14:56.000Z",
          "content:encoded": "",
          "content:encodedSnippet": "",
          "summary": ""
        },
        {
          "creator": "Kirsten Korosec",
          "title": "Kia opens orders for its flagship all-electric 2024 EV9 SUV",
          "link": "https://techcrunch.com/2023/10/16/kia-opens-orders-for-its-flagship-all-electric-2024-ev9-suv/",
          "pubDate": "Mon, 16 Oct 2023 21:12:42 +0000",
          "dc:creator": "Kirsten Korosec",
          "content": "",
          "contentSnippet": "",
          "guid": "https://techcrunch.com/?p=2615084",
          "categories": [
            "Transportation",
            "electric vehicles",
            "EV",
            "Kia",
            "Kia EV9"
          ],
          "isoDate": "2023-10-16T21:12:42.000Z",
          "content:encoded": "",
          "content:encodedSnippet": "",
          "summary": ""
        },
        {
          "creator": "Rebecca Bellan",
          "title": "Archer Aviation to launch air taxis in Abu Dhabi in 2026",
          "link": "https://techcrunch.com/2023/10/16/archer-aviation-to-launch-air-taxis-in-abu-dhabi-in-2026/",
          "pubDate": "Mon, 16 Oct 2023 21:09:45 +0000",
          "dc:creator": "Rebecca Bellan",
          "content": "",
          "contentSnippet": "",
          "guid": "https://techcrunch.com/?p=2615136",
          "categories": [
            "Transportation",
            "abu dhabi",
            "air taxis",
            "Archer Aviation",
            "eVTOL"
          ],
          "isoDate": "2023-10-16T21:09:45.000Z",
          "content:encoded": "",
          "content:encodedSnippet": "",
          "summary": ""
        }
      ],
      "feedUrl": "https://techcrunch.com/feed/",
      "image": {
        "link": "https://techcrunch.com/",
        "url": "https://techcrunch.com/wp-content/uploads/2015/02/cropped-cropped-favicon-gradient.png?w=32",
        "title": "TechCrunch",
        "width": "32",
        "height": "32"
      },
      "paginationLinks": {
        "self": "https://techcrunch.com/feed/"
      },
      "title": "TechCrunch",
      "description": "Startup and Technology News",
      "generator": "https://wordpress.org/?v=6.3.2",
      "link": "https://techcrunch.com/",
      "language": "en-US",
      "lastBuildDate": "Tue, 17 Oct 2023 06:15:43 +0000"
    },
    "the Verge": {
      "items": [
        {
          "title": "The Meta glassholes have arrived",
          "link": "https://www.theverge.com/23920102/meta-quest-3-in-public-privacy-recording-glassholes",
          "pubDate": "2023-10-17T00:08:33.000Z",
          "author": "Sean Hollister",
          "content": "",
          "contentSnippet": "",
          "id": "https://www.theverge.com/23920102/meta-quest-3-in-public-privacy-recording-glassholes",
          "isoDate": "2023-10-17T00:08:33.000Z",
          "content:encoded": "",
          "content:encodedSnippet": "",
          "summary": ""
        },
        {
          "title": "Sam Bankman-Fried was a bad friend, too",
          "link": "https://www.theverge.com/2023/10/16/23920125/sam-bankman-fried-nishad-singh-testimony-ftx-trial",
          "pubDate": "2023-10-16T23:34:26.000Z",
          "author": "Elizabeth Lopatto",
          "content": "",
          "contentSnippet": "",
          "id": "https://www.theverge.com/2023/10/16/23920125/sam-bankman-fried-nishad-singh-testimony-ftx-trial",
          "isoDate": "2023-10-16T23:34:26.000Z",
          "content:encoded": "",
          "content:encodedSnippet": "",
          "summary": ""
        },
        {
          "title": "Pixel 6 owners who use multiple profiles run into problems with Android 14",
          "link": "https://www.theverge.com/2023/10/16/23919957/pixel-6-android-14-upgrade-bugs-multiple-user-profiles",
          "pubDate": "2023-10-16T23:08:33.000Z",
          "author": "Umar Shakir",
          "content": "",
          "contentSnippet": "",
          "id": "https://www.theverge.com/2023/10/16/23919957/pixel-6-android-14-upgrade-bugs-multiple-user-profiles",
          "isoDate": "2023-10-16T23:08:33.000Z",
          "content:encoded": "",
          "content:encodedSnippet": "",
          "summary": ""
        },
        {
          "title": "Disney’s Gargoyles may live again — for real this time",
          "link": "https://www.theverge.com/2023/10/16/23920021/disney-reboot-animated-gargoyles-live-action",
          "pubDate": "2023-10-16T22:22:01.000Z",
          "author": "Alex Cranz",
          "content": "",
          "contentSnippet": "",
          "id": "https://www.theverge.com/2023/10/16/23920021/disney-reboot-animated-gargoyles-live-action",
          "isoDate": "2023-10-16T22:22:01.000Z",
          "content:encoded": "",
          "content:encodedSnippet": "",
          "summary": ""
        },
        {
          "title": "Apple rumors of refreshed iPads could mean new chips or new Pencils",
          "link": "https://www.theverge.com/2023/10/15/23917926/apple-ipad-air-mini-tablet-m2-a16-bionic-rumor",
          "pubDate": "2023-10-16T22:19:08.000Z",
          "author": "Wes Davis",
          "content": "",
          "contentSnippet": "",
          "id": "https://www.theverge.com/2023/10/15/23917926/apple-ipad-air-mini-tablet-m2-a16-bionic-rumor",
          "isoDate": "2023-10-16T22:19:08.000Z",
          "content:encoded": "",
          "content:encodedSnippet": "",
          "summary": ""
        },
        {
          "title": "The best phone to buy right now",
          "link": "https://www.theverge.com/22163811/best-phone",
          "pubDate": "2023-10-16T22:05:10.000Z",
          "author": "Allison Johnson",
          "content": "",
          "contentSnippet": "",
          "id": "https://www.theverge.com/22163811/best-phone",
          "isoDate": "2023-10-16T22:05:10.000Z",
          "content:encoded": "",
          "content:encodedSnippet": "",
          "summary": ""
        },
        {
          "title": "The best smartwatches for Android",
          "link": "https://www.theverge.com/23449363/best-android-smartwatches-wear-os",
          "pubDate": "2023-10-16T21:53:03.000Z",
          "author": "Victoria Song",
          "content": "",
          "contentSnippet": "",
          "id": "https://www.theverge.com/23449363/best-android-smartwatches-wear-os",
          "isoDate": "2023-10-16T21:53:03.000Z",
          "content:encoded": "",
          "content:encodedSnippet": "",
          "summary": ""
        },
        {
          "title": "The best Fitbits for your fitness and health",
          "link": "https://www.theverge.com/22982833/best-fitbit-watch-fitness-tracker",
          "pubDate": "2023-10-16T21:52:00.000Z",
          "author": "Victoria Song",
          "content": "",
          "contentSnippet": "",
          "id": "https://www.theverge.com/22982833/best-fitbit-watch-fitness-tracker",
          "isoDate": "2023-10-16T21:52:00.000Z",
          "content:encoded": "",
          "content:encodedSnippet": "",
          "summary": ""
        },
        {
          "title": "The best fitness trackers to buy right now",
          "link": "https://www.theverge.com/22985108/best-fitness-tracker",
          "pubDate": "2023-10-16T21:50:08.000Z",
          "author": "Victoria Song",
          "content": "",
          "contentSnippet": "",
          "id": "https://www.theverge.com/22985108/best-fitness-tracker",
          "isoDate": "2023-10-16T21:50:08.000Z",
          "content:encoded": "",
          "content:encodedSnippet": "",
          "summary": ""
        },
        {
          "title": "Here are the best Kindle deals right now",
          "link": "https://www.theverge.com/21539047/best-amazon-kindle-deals",
          "pubDate": "2023-10-16T21:40:46.000Z",
          "author": "Sheena Vasani",
          "content": "",
          "contentSnippet": "",
          "id": "https://www.theverge.com/21539047/best-amazon-kindle-deals",
          "isoDate": "2023-10-16T21:40:46.000Z",
          "content:encoded": "",
          "content:encodedSnippet": "",
          "summary": ""
        }
      ],
      "link": "https://www.theverge.com/",
      "title": "The Verge -  All Posts",
      "lastBuildDate": "2023-10-16T20:08:33-04:00"
    },
    "Hacker News": {
      "items": [
        {
          "creator": "donohoe",
          "title": "About half of Bandcamp employees have been laid off",
          "link": "https://www.theverge.com/2023/10/16/23919551/bandcamp-layoffs-epic-songtradr",
          "pubDate": "Mon, 16 Oct 2023 20:01:26 +0000",
          "dc:creator": "donohoe",
          "comments": "https://news.ycombinator.com/item?id=37905638",
          "content": "",
          "contentSnippet": "",
          "guid": "https://news.ycombinator.com/item?id=37905638",
          "isoDate": "2023-10-16T20:01:26.000Z",
          "content:encoded": "",
          "content:encodedSnippet": "",
          "summary": ""
        },
        {
          "creator": "wglb",
          "title": "Roundup herbicide ingredient connected to epidemic chronic kidney disease",
          "link": "https://phys.org/news/2023-10-roundup-herbicide-ingredient-epidemic-chronic.html",
          "pubDate": "Mon, 16 Oct 2023 19:41:08 +0000",
          "dc:creator": "wglb",
          "comments": "https://news.ycombinator.com/item?id=37905251",
          "content": "",
          "contentSnippet": "",
          "guid": "https://news.ycombinator.com/item?id=37905251",
          "isoDate": "2023-10-16T19:41:08.000Z",
          "content:encoded": "",
          "content:encodedSnippet": "",
          "summary": ""
        },
        {
          "creator": "cebert",
          "title": "LinkedIn is laying off nearly 700 employees",
          "link": "https://www.npr.org/2023/10/16/1206158638/linkedin-layoffs",
          "pubDate": "Mon, 16 Oct 2023 18:59:46 +0000",
          "dc:creator": "cebert",
          "comments": "https://news.ycombinator.com/item?id=37904518",
          "content": "",
          "contentSnippet": "",
          "guid": "https://news.ycombinator.com/item?id=37904518",
          "isoDate": "2023-10-16T18:59:46.000Z",
          "content:encoded": "",
          "content:encodedSnippet": "",
          "summary": ""
        },
        {
          "creator": "jkestner",
          "title": "Leaving Twitter had no effect on NPR's traffic",
          "link": "https://pluralistic.net/2023/10/14/freedom-of-reach/",
          "pubDate": "Mon, 16 Oct 2023 18:18:22 +0000",
          "dc:creator": "jkestner",
          "comments": "https://news.ycombinator.com/item?id=37903890",
          "content": "",
          "contentSnippet": "",
          "guid": "https://news.ycombinator.com/item?id=37903890",
          "isoDate": "2023-10-16T18:18:22.000Z",
          "content:encoded": "",
          "content:encodedSnippet": "",
          "summary": ""
        },
        {
          "creator": "tomduncalf",
          "title": "\"About half of Bandcamp was laid off today\"",
          "link": "https://twitter.com/modernistwitch/status/1713962311579234428",
          "pubDate": "Mon, 16 Oct 2023 17:25:33 +0000",
          "dc:creator": "tomduncalf",
          "comments": "https://news.ycombinator.com/item?id=37903172",
          "content": "",
          "contentSnippet": "",
          "guid": "https://news.ycombinator.com/item?id=37903172",
          "isoDate": "2023-10-16T17:25:33.000Z",
          "content:encoded": "",
          "content:encodedSnippet": "",
          "summary": ""
        },
        {
          "creator": "jthomaslm",
          "title": "Launch HN: Radical (YC W23) – Autonomous high-altitude solar aircraft",
          "link": "https://news.ycombinator.com/item?id=37901120",
          "pubDate": "Mon, 16 Oct 2023 15:23:57 +0000",
          "dc:creator": "jthomaslm",
          "comments": "https://news.ycombinator.com/item?id=37901120",
          "content": "",
          "contentSnippet": "",
          "guid": "https://news.ycombinator.com/item?id=37901120",
          "isoDate": "2023-10-16T15:23:57.000Z",
          "content:encoded": "",
          "content:encodedSnippet": "",
          "summary": ""
        },
        {
          "creator": "ingve",
          "title": "Better HTTP server routing in Go 1.22",
          "link": "https://eli.thegreenplace.net/2023/better-http-server-routing-in-go-122/",
          "pubDate": "Mon, 16 Oct 2023 12:38:14 +0000",
          "dc:creator": "ingve",
          "comments": "https://news.ycombinator.com/item?id=37898999",
          "content": "",
          "contentSnippet": "",
          "guid": "https://news.ycombinator.com/item?id=37898999",
          "isoDate": "2023-10-16T12:38:14.000Z",
          "content:encoded": "",
          "content:encodedSnippet": "",
          "summary": ""
        },
        {
          "creator": "bmer",
          "title": "C Is Not a Low-level Language (2018)",
          "link": "https://queue.acm.org/detail.cfm?id=3212479",
          "pubDate": "Mon, 16 Oct 2023 10:46:10 +0000",
          "dc:creator": "bmer",
          "comments": "https://news.ycombinator.com/item?id=37897946",
          "content": "",
          "contentSnippet": "",
          "guid": "https://news.ycombinator.com/item?id=37897946",
          "isoDate": "2023-10-16T10:46:10.000Z",
          "content:encoded": "",
          "content:encodedSnippet": "",
          "summary": ""
        },
        {
          "creator": "akyuu",
          "title": "FreeTube – The Private YouTube Client",
          "link": "https://github.com/FreeTubeApp/FreeTube",
          "pubDate": "Mon, 16 Oct 2023 10:40:17 +0000",
          "dc:creator": "akyuu",
          "comments": "https://news.ycombinator.com/item?id=37897916",
          "content": "",
          "contentSnippet": "",
          "guid": "https://news.ycombinator.com/item?id=37897916",
          "isoDate": "2023-10-16T10:40:17.000Z",
          "content:encoded": "",
          "content:encodedSnippet": "",
          "summary": ""
        },
        {
          "creator": "thunderbong",
          "title": "Cockpit: Web-based graphical interface for servers",
          "link": "https://cockpit-project.org/",
          "pubDate": "Mon, 16 Oct 2023 02:48:21 +0000",
          "dc:creator": "thunderbong",
          "comments": "https://news.ycombinator.com/item?id=37895446",
          "content": "",
          "contentSnippet": "",
          "guid": "https://news.ycombinator.com/item?id=37895446",
          "isoDate": "2023-10-16T02:48:21.000Z",
          "content:encoded": "",
          "content:encodedSnippet": "",
          "summary": ""
        }
      ],
      "feedUrl": "https://hnrss.org/best",
      "paginationLinks": {
        "self": "https://hnrss.org/best"
      },
      "title": "Hacker News: Best",
      "description": "Hacker News RSS",
      "generator": "hnrss v2.1.1",
      "link": "https://news.ycombinator.com/best",
      "lastBuildDate": "Tue, 17 Oct 2023 06:25:01 +0000",
      "docs": "https://hnrss.org/"
    },
    "Hacker News Top 30": {
      "items": [
        {
          "creator": "github-actions[bot]",
          "title": "Hacker News Daily Top 30 @2023-10-17",
          "link": "https://github.com/meixger/hackernews-daily/issues/395",
          "pubDate": "Tue, 17 Oct 2023 06:12:29 GMT",
          "author": "github-actions[bot]",
          "content": "",
          "contentSnippet": "",
          "guid": "https://github.com/meixger/hackernews-daily/issues/395",
          "isoDate": "2023-10-17T06:12:29.000Z",
          "content:encoded": "",
          "content:encodedSnippet": "",
          "summary": ""
        },
        {
          "creator": "github-actions[bot]",
          "title": "Hacker News Daily Top 30 @2023-10-16",
          "link": "https://github.com/meixger/hackernews-daily/issues/394",
          "pubDate": "Mon, 16 Oct 2023 06:12:51 GMT",
          "author": "github-actions[bot]",
          "content": "",
          "contentSnippet": "",
          "guid": "https://github.com/meixger/hackernews-daily/issues/394",
          "isoDate": "2023-10-16T06:12:51.000Z",
          "content:encoded": "",
          "content:encodedSnippet": "",
          "summary": ""
        },
        {
          "creator": "github-actions[bot]",
          "title": "Hacker News Daily Top 30 @2023-10-15",
          "link": "https://github.com/meixger/hackernews-daily/issues/393",
          "pubDate": "Sun, 15 Oct 2023 06:11:11 GMT",
          "author": "github-actions[bot]",
          "content": "",
          "contentSnippet": "",
          "guid": "https://github.com/meixger/hackernews-daily/issues/393",
          "isoDate": "2023-10-15T06:11:11.000Z",
          "content:encoded": "",
          "content:encodedSnippet": "",
          "summary": ""
        },
        {
          "creator": "github-actions[bot]",
          "title": "Hacker News Daily Top 30 @2023-10-14",
          "link": "https://github.com/meixger/hackernews-daily/issues/392",
          "pubDate": "Sat, 14 Oct 2023 06:11:18 GMT",
          "author": "github-actions[bot]",
          "content": "",
          "contentSnippet": "",
          "guid": "https://github.com/meixger/hackernews-daily/issues/392",
          "isoDate": "2023-10-14T06:11:18.000Z",
          "content:encoded": "",
          "content:encodedSnippet": "",
          "summary": ""
        },
        {
          "creator": "github-actions[bot]",
          "title": "Hacker News Daily Top 30 @2023-10-13",
          "link": "https://github.com/meixger/hackernews-daily/issues/391",
          "pubDate": "Fri, 13 Oct 2023 06:12:29 GMT",
          "author": "github-actions[bot]",
          "content": "",
          "contentSnippet": "",
          "guid": "https://github.com/meixger/hackernews-daily/issues/391",
          "isoDate": "2023-10-13T06:12:29.000Z",
          "content:encoded": "",
          "content:encodedSnippet": "",
          "summary": ""
        },
        {
          "creator": "github-actions[bot]",
          "title": "Hacker News Daily Top 30 @2023-10-12",
          "link": "https://github.com/meixger/hackernews-daily/issues/390",
          "pubDate": "Thu, 12 Oct 2023 06:12:11 GMT",
          "author": "github-actions[bot]",
          "content": "",
          "contentSnippet": "",
          "guid": "https://github.com/meixger/hackernews-daily/issues/390",
          "isoDate": "2023-10-12T06:12:11.000Z",
          "content:encoded": "",
          "content:encodedSnippet": "",
          "summary": ""
        },
        {
          "creator": "github-actions[bot]",
          "title": "Hacker News Daily Top 30 @2023-10-11",
          "link": "https://github.com/meixger/hackernews-daily/issues/389",
          "pubDate": "Wed, 11 Oct 2023 06:12:37 GMT",
          "author": "github-actions[bot]",
          "content": "",
          "contentSnippet": "",
          "guid": "https://github.com/meixger/hackernews-daily/issues/389",
          "isoDate": "2023-10-11T06:12:37.000Z",
          "content:encoded": "",
          "content:encodedSnippet": "",
          "summary": ""
        }
      ],
      "feedUrl": "https://rsshub.app/github/issue/meixger/hackernews-daily",
      "paginationLinks": {
        "self": "https://rsshub.app/github/issue/meixger/hackernews-daily"
      },
      "title": "meixger/hackernews-daily Issues",
      "description": "meixger/hackernews-daily Issues - Made with love by RSSHub(https://github.com/DIYgod/RSSHub)",
      "webMaster": "i@diygod.me (DIYgod)",
      "generator": "RSSHub",
      "link": "https://github.com/meixger/hackernews-daily/issues",
      "language": "zh-cn",
      "lastBuildDate": "Tue, 17 Oct 2023 06:50:13 GMT",
      "ttl": "120"
    }
  }
}